Metadata-Version: 1.1
Name: rdiff-trimmer
Version: 0.3.1
Summary: Get rid of the old rdiff-backup increments from your backup.
Home-page: https://github.com/Bystroushaak/rdiff_trimmer
Author: Bystroushaak
Author-email: bystrousak@kitakitsune.org
License: MIT
Platform: UNKNOWN
Classifier: License :: OSI Approved :: MIT License
Classifier: Programming Language :: Python
Classifier: Programming Language :: Python :: 2.7
